pkgAnant/__init__.py
pkgAnant/passwd.py
pkgAnant-4.1.3.dist-info/LICENSE.txt
pkgAnant-4.1.3.dist-info/METADATA
pkgAnant-4.1.3.dist-info/WHEEL
pkgAnant-4.1.3.dist-info/top_level.txt
pkgAnant-4.1.3.dist-info/RECORD
