Metadata-Version: 2.1
Name: pkgAnant
Version: 4.1.3
Summary: password generator package
Home-page: UNKNOWN
Author: Anant Chaudhary
License: UNKNOWN
Platform: UNKNOWN
Classifier: Programming Language :: Python :: 3
Classifier: License :: OSI Approved :: MIT License
Classifier: Operating System :: OS Independent
Requires-Python: >=3.6
